odoo/addons/product_restricted_type/README.rst
odoo/addons/product_restricted_type/__init__.py
odoo/addons/product_restricted_type/__manifest__.py
odoo/addons/product_restricted_type/i18n/ca.po
odoo/addons/product_restricted_type/i18n/es.po
odoo/addons/product_restricted_type/i18n/it.po
odoo/addons/product_restricted_type/i18n/product_restricted_type.pot
odoo/addons/product_restricted_type/models/__init__.py
odoo/addons/product_restricted_type/models/product_category.py
odoo/addons/product_restricted_type/models/product_product.py
odoo/addons/product_restricted_type/models/product_template.py
odoo/addons/product_restricted_type/readme/CONTRIBUTORS.md
odoo/addons/product_restricted_type/readme/DESCRIPTION.md
odoo/addons/product_restricted_type/readme/USAGE.md
odoo/addons/product_restricted_type/static/description/icon.png
odoo/addons/product_restricted_type/static/description/index.html
odoo/addons/product_restricted_type/tests/__init__.py
odoo/addons/product_restricted_type/tests/test_product_restricted_type.py
odoo/addons/product_restricted_type/views/product_category_views.xml
odoo/addons/product_restricted_type/views/product_views.xml
odoo_addon_product_restricted_type-17.0.1.0.0.2.dist-info/METADATA
odoo_addon_product_restricted_type-17.0.1.0.0.2.dist-info/WHEEL
odoo_addon_product_restricted_type-17.0.1.0.0.2.dist-info/top_level.txt
odoo_addon_product_restricted_type-17.0.1.0.0.2.dist-info/RECORD
